{"type":"list","label":null,"list":[{"type":"list","label":"let","list":[{"type":"text","text":"digit-to-chr","label":null},{"type":"mark","label":"cr"},{"type":"list","label":"func","list":[{"type":"list","label":null,"list":[{"type":"text","text":"digit","label":null}]},{"type":"mark","label":"cr"},{"type":"list","label":null,"list":[{"type":"text","text":"chr","label":null},{"type":"list","label":"infix","list":[{"type":"list","label":"infix","list":[{"type":"text","text":"digit","label":null},{"type":"text","text":"%","label":null},{"type":"text","text":"10","label":null}]},{"type":"text","text":"+","label":null},{"type":"list","label":null,"list":[{"type":"text","text":"ord","label":null},{"type":"text","text":"0","label":"string"}]}]}]}]}]},{"type":"mark","label":"cr"},{"type":"list","label":"let","list":[{"type":"text","text":"print-number","label":null},{"type":"mark","label":"cr"},{"type":"list","label":"func","list":[{"type":"list","label":null,"list":[{"type":"text","text":"value","label":null}]},{"type":"mark","label":"cr"},{"type":"list","label":"let","list":[{"type":"text","text":"string","label":null},{"type":"text","text":"","label":"string"}]},{"type":"mark","label":"cr"},{"type":"list","label":"cond","list":[{"type":"list","label":null,"list":[{"type":"list","label":"infix","list":[{"type":"text","text":"value","label":null},{"type":"text","text":"=","label":null},{"type":"text","text":"0","label":null}]},{"type":"mark","label":"cr"},{"type":"list","label":"let","list":[{"type":"text","text":"string","label":null},{"type":"text","text":"0","label":"string"}]}]}]},{"type":"mark","label":"cr"},{"type":"list","label":"while","list":[{"type":"list","label":"infix","list":[{"type":"text","text":"value","label":null},{"type":"text","text":">","label":null},{"type":"text","text":"0","label":null}]},{"type":"mark","label":"cr"},{"type":"list","label":"let","list":[{"type":"text","text":"string","label":null},{"type":"list","label":null,"list":[{"type":"text","text":"cat","label":null},{"type":"list","label":null,"list":[{"type":"text","text":"digit-to-chr","label":null},{"type":"text","text":"value","label":null}]},{"type":"text","text":"string","label":null}]}]},{"type":"mark","label":"cr"},{"type":"list","label":"let","list":[{"type":"text","text":"value","label":null},{"type":"list","label":"infix","list":[{"type":"text","text":"value","label":null},{"type":"text","text":"//","label":null},{"type":"text","text":"10","label":null}]}]}]},{"type":"mark","label":"cr"},{"type":"list","label":null,"list":[{"type":"text","text":"file-write","label":null},{"type":"text","text":"stdout","label":null},{"type":"list","label":null,"list":[{"type":"text","text":"cat","label":null},{"type":"text","text":"string","label":null},{"type":"text","text":"\n","label":"string"}]}]}]}]},{"type":"mark","label":"cr"},{"type":"list","label":"let","list":[{"type":"text","text":"print","label":null},{"type":"mark","label":"cr"},{"type":"list","label":"func","list":[{"type":"list","label":null,"list":[{"type":"text","text":"value","label":null}]},{"type":"mark","label":"cr"},{"type":"list","label":null,"list":[{"type":"text","text":"file-write","label":null},{"type":"text","text":"stdout","label":null},{"type":"list","label":null,"list":[{"type":"text","text":"cat","label":null},{"type":"text","text":"value","label":null},{"type":"text","text":"\n","label":"string"}]}]}]}]},{"type":"mark","label":"cr"},{"type":"list","label":"let","list":[{"type":"text","text":"read-integer","label":null},{"type":"mark","label":"cr"},{"type":"list","label":"func","list":[{"type":"list","label":null,"list":[{"type":"text","text":"fd","label":null}]},{"type":"mark","label":"cr"},{"type":"list","label":"let","list":[{"type":"text","text":"buffer","label":null},{"type":"list","label":null,"list":[{"type":"text","text":"arraybuffer","label":null},{"type":"text","text":"4","label":null}]}]},{"type":"mark","label":"cr"},{"type":"list","label":null,"list":[{"type":"text","text":"file-read","label":null},{"type":"text","text":"fd","label":null},{"type":"text","text":"buffer","label":null}]},{"type":"mark","label":"cr"},{"type":"list","label":"infix","list":[{"type":"list","label":"infix","list":[{"type":"list","label":"infix","list":[{"type":"list","label":"infix","list":[{"type":"list","label":null,"list":[{"type":"text","text":"idx","label":null},{"type":"text","text":"buffer","label":null},{"type":"text","text":"0","label":null}]},{"type":"text","text":"<<","label":null},{"type":"text","text":"0","label":null}]},{"type":"mark","label":"cr"},{"type":"text","text":"|","label":null},{"type":"list","label":"infix","list":[{"type":"list","label":null,"list":[{"type":"text","text":"idx","label":null},{"type":"text","text":"buffer","label":null},{"type":"text","text":"1","label":null}]},{"type":"text","text":"<<","label":null},{"type":"text","text":"8","label":null}]}]},{"type":"mark","label":"cr"},{"type":"text","text":"|","label":null},{"type":"list","label":"infix","list":[{"type":"list","label":null,"list":[{"type":"text","text":"idx","label":null},{"type":"text","text":"buffer","label":null},{"type":"text","text":"2","label":null}]},{"type":"text","text":"<<","label":null},{"type":"text","text":"16","label":null}]}]},{"type":"mark","label":"cr"},{"type":"text","text":"|","label":null},{"type":"list","label":"infix","list":[{"type":"list","label":null,"list":[{"type":"text","text":"idx","label":null},{"type":"text","text":"buffer","label":null},{"type":"text","text":"3","label":null}]},{"type":"text","text":"<<","label":null},{"type":"text","text":"24","label":null}]}]}]}]},{"type":"mark","label":"cr"},{"type":"list","label":"let","list":[{"type":"text","text":"fd","label":null},{"type":"list","label":null,"list":[{"type":"text","text":"file-open","label":null},{"type":"text","text":"stdlib.blip","label":"string"}]}]},{"type":"mark","label":"cr"},{"type":"list","label":"let","list":[{"type":"text","text":"i","label":null},{"type":"text","text":"0","label":null}]},{"type":"mark","label":"cr"},{"type":"list","label":"let","list":[{"type":"text","text":"data","label":null},{"type":"list","label":null,"list":[{"type":"text","text":"arraybuffer","label":null},{"type":"text","text":"16","label":null}]}]},{"type":"mark","label":"cr"},{"type":"list","label":null,"list":[{"type":"text","text":"file-read","label":null},{"type":"text","text":"fd","label":null},{"type":"text","text":"data","label":null}]},{"type":"mark","label":"cr"},{"type":"list","label":"while","list":[{"type":"list","label":"infix","list":[{"type":"text","text":"i","label":null},{"type":"text","text":"<","label":null},{"type":"text","text":"16","label":null}]},{"type":"mark","label":"cr"},{"type":"list","label":null,"list":[{"type":"text","text":"print-number","label":null},{"type":"list","label":null,"list":[{"type":"text","text":"idx","label":null},{"type":"text","text":"data","label":null},{"type":"text","text":"i","label":null}]}]},{"type":"mark","label":"cr"},{"type":"list","label":"let","list":[{"type":"text","text":"i","label":null},{"type":"list","label":"infix","list":[{"type":"text","text":"i","label":null},{"type":"text","text":"+","label":null},{"type":"text","text":"1","label":null}]}]}]},{"type":"mark","label":"cr"},{"type":"list","label":"let","list":[{"type":"text","text":"read-node","label":null},{"type":"mark","label":"cr"},{"type":"list","label":"func","list":[{"type":"list","label":null,"list":[{"type":"text","text":"fd","label":null}]},{"type":"mark","label":"cr"},{"type":"list","label":"let","list":[{"type":"text","text":"info","label":null},{"type":"list","label":null,"list":[{"type":"text","text":"read-integer","label":null},{"type":"text","text":"fd","label":null}]}]},{"type":"mark","label":"cr"},{"type":"list","label":"let","list":[{"type":"text","text":"type","label":null},{"type":"list","label":"infix","list":[{"type":"text","text":"info","label":null},{"type":"text","text":"&","label":null},{"type":"text","text":"3","label":null}]}]},{"type":"mark","label":"cr"},{"type":"list","label":"let","list":[{"type":"text","text":"uid-length","label":null},{"type":"list","label":"infix","list":[{"type":"list","label":"infix","list":[{"type":"text","text":"info","label":null},{"type":"text","text":">>","label":null},{"type":"text","text":"2","label":null}]},{"type":"text","text":"&","label":null},{"type":"text","text":"127","label":null}]}]},{"type":"mark","label":"cr"},{"type":"list","label":"let","list":[{"type":"text","text":"label-length","label":null},{"type":"list","label":"infix","list":[{"type":"list","label":"infix","list":[{"type":"text","text":"info","label":null},{"type":"text","text":">>","label":null},{"type":"text","text":"9","label":null}]},{"type":"text","text":"&","label":null},{"type":"text","text":"127","label":null}]}]},{"type":"mark","label":"cr"},{"type":"list","label":"let","list":[{"type":"text","text":"data-length","label":null},{"type":"list","label":"infix","list":[{"type":"list","label":"infix","list":[{"type":"text","text":"info","label":null},{"type":"text","text":">>","label":null},{"type":"text","text":"16","label":null}]},{"type":"text","text":"&","label":null},{"type":"list","label":"infix","list":[{"type":"list","label":"infix","list":[{"type":"text","text":"256","label":null},{"type":"text","text":"*","label":null},{"type":"text","text":"256","label":null}]},{"type":"text","text":"-","label":null},{"type":"text","text":"1","label":null}]}]}]},{"type":"mark","label":"cr"},{"type":"list","label":"let","list":[{"type":"text","text":"uid","label":null},{"type":"list","label":null,"list":[{"type":"text","text":"arraybuffer","label":null},{"type":"text","text":"uid-length","label":null}]}]},{"type":"mark","label":"cr"},{"type":"list","label":"let","list":[{"type":"text","text":"label","label":null},{"type":"list","label":null,"list":[{"type":"text","text":"arraybuffer","label":null},{"type":"text","text":"label-length","label":null}]}]},{"type":"mark","label":"cr"},{"type":"list","label":null,"list":[{"type":"text","text":"file-read","label":null},{"type":"text","text":"fd","label":null},{"type":"text","text":"uid","label":null}]},{"type":"mark","label":"cr"},{"type":"list","label":null,"list":[{"type":"text","text":"file-read","label":null},{"type":"text","text":"fd","label":null},{"type":"text","text":"label","label":null}]},{"type":"mark","label":"cr"},{"type":"list","label":"cond","list":[{"type":"list","label":null,"list":[{"type":"list","label":"infix","list":[{"type":"text","text":"type","label":null},{"type":"text","text":"=","label":null},{"type":"text","text":"0","label":null}]},{"type":"mark","label":"cr"},{"type":"list","label":null,"list":[{"type":"text","text":"print","label":null},{"type":"text","text":"list","label":"string"}]},{"type":"mark","label":"cr"},{"type":"list","label":"let","list":[{"type":"text","text":"i","label":null},{"type":"text","text":"0","label":null}]},{"type":"mark","label":"cr"},{"type":"list","label":"while","list":[{"type":"list","label":"infix","list":[{"type":"text","text":"i","label":null},{"type":"text","text":"<","label":null},{"type":"text","text":"data-length","label":null}]},{"type":"mark","label":"cr"},{"type":"list","label":null,"list":[{"type":"text","text":"read-node","label":null},{"type":"text","text":"fd","label":null}]},{"type":"mark","label":"cr"},{"type":"list","label":"let","list":[{"type":"text","text":"i","label":null},{"type":"list","label":"infix","list":[{"type":"text","text":"i","label":null},{"type":"text","text":"+","label":null},{"type":"text","text":"1","label":null}]}]}]}]},{"type":"list","label":null,"list":[{"type":"list","label":"infix","list":[{"type":"text","text":"type","label":null},{"type":"text","text":"=","label":null},{"type":"text","text":"1","label":null}]},{"type":"mark","label":"cr"},{"type":"list","label":null,"list":[{"type":"text","text":"print","label":null},{"type":"text","text":"text","label":"string"}]},{"type":"mark","label":"cr"},{"type":"list","label":"let","list":[{"type":"text","text":"data","label":null},{"type":"list","label":null,"list":[{"type":"text","text":"arraybuffer","label":null},{"type":"text","text":"data-length","label":null}]}]},{"type":"mark","label":"cr"},{"type":"list","label":null,"list":[{"type":"text","text":"file-read","label":null},{"type":"text","text":"fd","label":null},{"type":"text","text":"data","label":null}]}]},{"type":"list","label":null,"list":[{"type":"list","label":"infix","list":[{"type":"text","text":"type","label":null},{"type":"text","text":"=","label":null},{"type":"text","text":"2","label":null}]},{"type":"mark","label":"cr"},{"type":"list","label":null,"list":[{"type":"text","text":"print","label":null},{"type":"text","text":"data","label":"string"}]},{"type":"mark","label":"cr"},{"type":"list","label":"let","list":[{"type":"text","text":"data","label":null},{"type":"list","label":null,"list":[{"type":"text","text":"arraybuffer","label":null},{"type":"text","text":"data-length","label":null}]}]},{"type":"mark","label":"cr"},{"type":"list","label":null,"list":[{"type":"text","text":"file-read","label":null},{"type":"text","text":"fd","label":null},{"type":"text","text":"data","label":null}]}]},{"type":"list","label":null,"list":[{"type":"list","label":"infix","list":[{"type":"text","text":"type","label":null},{"type":"text","text":"=","label":null},{"type":"text","text":"3","label":null}]},{"type":"mark","label":"cr"},{"type":"text","text":"print","label":null},{"type":"text","text":"mark","label":"string"}]}]}]}]},{"type":"mark","label":"cr"},{"type":"list","label":null,"list":[{"type":"text","text":"read-node","label":null},{"type":"text","text":"fd","label":null}]},{"type":"mark","label":"cr"}]}